{
  "_class": "symbolInstance",
  "booleanOperation": -1,
  "clippingMaskMode": 0,
  "do_objectID": "343AE7F6-39F3-4E73-BC7E-E5992DD45CD1",
  "exportOptions": {
    "_class": "exportOptions",
    "do_objectID": "A063A9BC-3E15-4C87-BE20-62876640B6D7",
    "exportFormats": [
    ],
    "includedLayerIds": [
    ],
    "layerOptions": 0,
    "shouldTrim": false
  },
  "frame": {
    "_class": "rect",
    "constrainProportions": false,
    "do_objectID": "E09F5298-83C4-4667-8BD8-FD8CA16FC1F7",
    "height": 29,
    "width": 128,
    "x": 0,
    "y": 116
  },
  "hasClippingMask": false,
  "horizontalSpacing": 0,
  "isFixedToViewport": false,
  "isFlippedHorizontal": false,
  "isFlippedVertical": false,
  "isLocked": false,
  "isVisible": true,
  "layerListExpandedType": 0,
  "name": "unit copy 4",
  "nameIsFixed": false,
  "overrideValues": [
  ],
  "resizingConstraint": 63,
  "resizingType": 0,
  "rotation": 0,
  "scale": 1,
  "shouldBreakMaskChain": false,
  "style": {
    "_class": "style",
    "do_objectID": "67175C51-9E7C-461C-8685-48201D7EB4D4",
    "endMarkerType": 0,
    "miterLimit": 10,
    "startMarkerType": 0,
    "windingRule": 1
  },
  "symbolID": "3F22EDF5-5D68-47F1-AE16-D6DA454EF5A1",
  "verticalSpacing": 0
}