{
  "_class": "shapeGroup",
  "booleanOperation": -1,
  "clippingMaskMode": 0,
  "do_objectID": "1299BF12-24A4-4F2C-BC34-89F6B825199F",
  "exportOptions": {
    "_class": "exportOptions",
    "do_objectID": "6CF5C489-4268-4401-9456-D9A018215548",
    "exportFormats": [
    ],
    "includedLayerIds": [
    ],
    "layerOptions": 0,
    "shouldTrim": false
  },
  "frame": {
    "_class": "rect",
    "constrainProportions": false,
    "do_objectID": "986225EE-2F13-4E24-86C4-04B46FBAD61D",
    "height": 61,
    "width": 304,
    "x": 405,
    "y": 255
  },
  "hasClickThrough": false,
  "hasClippingMask": false,
  "isFixedToViewport": false,
  "isFlippedHorizontal": false,
  "isFlippedVertical": false,
  "isLocked": false,
  "isVisible": true,
  "layerListExpandedType": 0,
  "layers": [
    {
      "class": "rectangle",
      "id": "69B9974D-660D-4C71-BD2F-A77682C864C1"
    }
  ],
  "name": "Rectangle Copy 3",
  "nameIsFixed": false,
  "resizingConstraint": 63,
  "resizingType": 0,
  "rotation": 0,
  "shouldBreakMaskChain": false,
  "style": {
    "_class": "style",
    "borders": [
      {
        "_class": "border",
        "color": {
          "_class": "color",
          "alpha": 1,
          "blue": 0.8862745098039215,
          "green": 0.4823529411764709,
          "red": 0.1176470588235294
        },
        "fillType": 0,
        "isEnabled": true,
        "position": 1,
        "thickness": 4
      }
    ],
    "do_objectID": "5FB4B6D6-03CA-45DA-AB3F-0A4621B7F7B9",
    "endMarkerType": 0,
    "fills": [
      {
        "_class": "fill",
        "color": {
          "_class": "color",
          "alpha": 1,
          "blue": 0.847,
          "green": 0.847,
          "red": 0.847
        },
        "fillType": 0,
        "isEnabled": false,
        "noiseIndex": 0,
        "noiseIntensity": 0,
        "patternFillType": 1,
        "patternTileScale": 1
      }
    ],
    "miterLimit": 10,
    "startMarkerType": 0,
    "windingRule": 0
  },
  "windingRule": 0
}