{
  "_class": "rectangle",
  "booleanOperation": -1,
  "clippingMaskMode": 0,
  "do_objectID": "1C36E456-257D-40C2-9C78-4C64A6AB926B",
  "edited": false,
  "exportOptions": {
    "_class": "exportOptions",
    "do_objectID": "B1ECDC65-19DE-4298-8337-3158AC492361",
    "exportFormats": [
    ],
    "includedLayerIds": [
    ],
    "layerOptions": 0,
    "shouldTrim": false
  },
  "fixedRadius": 23.80408163265306,
  "frame": {
    "_class": "rect",
    "constrainProportions": false,
    "do_objectID": "E0BD0D9F-D33D-4BDE-9919-191B7C217006",
    "height": 381.2091152815015,
    "width": 179.3568147013783,
    "x": 5.880551301684534,
    "y": 4.415549597855229
  },
  "hasClippingMask": false,
  "hasConvertedToNewRoundCorners": true,
  "isClosed": true,
  "isFixedToViewport": false,
  "isFlippedHorizontal": false,
  "isFlippedVertical": false,
  "isLocked": false,
  "isVisible": true,
  "layerListExpandedType": 1,
  "name": "inner",
  "nameIsFixed": true,
  "pointRadiusBehaviour": 0,
  "points": [
    {
      "_class": "curvePoint",
      "cornerRadius": 23.80408163265306,
      "curveFrom": "{0, 0}",
      "curveMode": 1,
      "curveTo": "{0, 0}",
      "hasCurveFrom": false,
      "hasCurveTo": false,
      "point": "{0, 0}"
    },
    {
      "_class": "curvePoint",
      "cornerRadius": 23.80408163265306,
      "curveFrom": "{1, 0}",
      "curveMode": 1,
      "curveTo": "{1, 0}",
      "hasCurveFrom": false,
      "hasCurveTo": false,
      "point": "{1, 0}"
    },
    {
      "_class": "curvePoint",
      "cornerRadius": 23.80408163265306,
      "curveFrom": "{1, 1}",
      "curveMode": 1,
      "curveTo": "{1, 1}",
      "hasCurveFrom": false,
      "hasCurveTo": false,
      "point": "{1, 1}"
    },
    {
      "_class": "curvePoint",
      "cornerRadius": 23.80408163265306,
      "curveFrom": "{0, 1}",
      "curveMode": 1,
      "curveTo": "{0, 1}",
      "hasCurveFrom": false,
      "hasCurveTo": false,
      "point": "{0, 1}"
    }
  ],
  "resizingConstraint": 63,
  "resizingType": 0,
  "rotation": 0,
  "shouldBreakMaskChain": false,
  "style": {
    "_class": "style",
    "blur": {
      "_class": "blur",
      "center": "{0.5, 0.5}",
      "do_objectID": "BB10F71F-2215-4BC7-A86E-96EE48B1CFCE",
      "isEnabled": false,
      "motionAngle": 0,
      "radius": 2.204081632653061,
      "saturation": 1,
      "type": 0
    },
    "borders": [
      {
        "_class": "border",
        "color": {
          "_class": "color",
          "alpha": 0.1,
          "blue": 0,
          "green": 0,
          "red": 0
        },
        "fillType": 0,
        "isEnabled": true,
        "position": 0,
        "thickness": 0.7346938775510203
      }
    ],
    "do_objectID": "2AA34395-C9D5-4796-B50E-E6CE13226358",
    "endMarkerType": 0,
    "innerShadows": [
      {
        "_class": "innerShadow",
        "blurRadius": 1,
        "color": {
          "_class": "color",
          "alpha": 1,
          "blue": 0.1019607843137255,
          "green": 0.1019607843137255,
          "red": 0.1019607843137255
        },
        "contextSettings": {
          "_class": "graphicsContextSettings",
          "blendMode": 5,
          "opacity": 1
        },
        "isEnabled": true,
        "offsetX": 0,
        "offsetY": 1,
        "spread": 0
      }
    ],
    "miterLimit": 10,
    "startMarkerType": 0,
    "windingRule": 1
  },
  "userInfo": {
    "com.animaapp.stc-sketch-plugin": {
      "kModelPropertiesKey": {
      }
    }
  }
}