{
  "_class": "symbolInstance",
  "booleanOperation": -1,
  "clippingMaskMode": 0,
  "do_objectID": "2C41AA46-1AA5-40E2-BE3F-529A38C05A35",
  "exportOptions": {
    "_class": "exportOptions",
    "do_objectID": "626CF9FB-4BBD-49EE-AAC7-9DD10E505EB0",
    "exportFormats": [
    ],
    "includedLayerIds": [
    ],
    "layerOptions": 0,
    "shouldTrim": false
  },
  "frame": {
    "_class": "rect",
    "constrainProportions": false,
    "do_objectID": "A8CFCF31-631F-45E1-B697-1E7612B41712",
    "height": 568,
    "width": 320,
    "x": 0,
    "y": -12
  },
  "hasClippingMask": false,
  "horizontalSpacing": 0,
  "isFixedToViewport": false,
  "isFlippedHorizontal": false,
  "isFlippedVertical": false,
  "isLocked": false,
  "isVisible": false,
  "layerListExpandedType": 0,
  "name": "iPhone X/iPhone X Frame",
  "nameIsFixed": false,
  "overrideValues": [
  ],
  "resizingConstraint": 63,
  "resizingType": 0,
  "rotation": 0,
  "scale": 1,
  "shouldBreakMaskChain": false,
  "style": {
    "_class": "style",
    "do_objectID": "48BAE6BF-8F5F-4293-AC8B-C64B6ECEAB32",
    "endMarkerType": 0,
    "miterLimit": 10,
    "startMarkerType": 0,
    "windingRule": 1
  },
  "symbolID": "70339D84-EA02-4344-A642-B520439AE881",
  "verticalSpacing": 0
}