{
  "_class": "bitmap",
  "booleanOperation": -1,
  "clippingMask": "{{0, 0}, {1, 1}}",
  "clippingMaskMode": 0,
  "do_objectID": "A4982CD0-CD9F-4563-A9AF-FD87286F12A6",
  "exportOptions": {
    "_class": "exportOptions",
    "do_objectID": "0CBF94BD-9105-4B1A-BF6A-839D7B042F1F",
    "exportFormats": [
    ],
    "includedLayerIds": [
    ],
    "layerOptions": 0,
    "shouldTrim": false
  },
  "fillReplacesImage": false,
  "frame": {
    "_class": "rect",
    "constrainProportions": true,
    "do_objectID": "8A1CD98C-5ADC-44F1-B1B4-2EAA5B8D9CC9",
    "height": 292,
    "width": 476,
    "x": 269,
    "y": 36
  },
  "hasClippingMask": false,
  "image": {
    "_class": "MSJSONFileReference",
    "_ref": "images/8e11bc16bb8e16ec06803697c7111c0f5f7ddfb1.png",
    "_ref_class": "MSImageData"
  },
  "intendedDPI": 72,
  "isFixedToViewport": false,
  "isFlippedHorizontal": false,
  "isFlippedVertical": false,
  "isLocked": false,
  "isVisible": true,
  "layerListExpandedType": 0,
  "name": "lsc_capture",
  "nameIsFixed": false,
  "resizingConstraint": 63,
  "resizingType": 0,
  "rotation": 0,
  "shouldBreakMaskChain": false,
  "style": {
    "_class": "style",
    "do_objectID": "2379E63B-4A06-4E20-979B-8ECEB6DCD45D",
    "endMarkerType": 0,
    "miterLimit": 10,
    "startMarkerType": 0,
    "windingRule": 1
  }
}